mollie/__init__.py
mollie/py.typed
mollie/api/__init__.py
mollie/api/client.py
mollie/api/error.py
mollie/api/version.py
mollie/api/objects/__init__.py
mollie/api/objects/balance.py
mollie/api/objects/balance_report.py
mollie/api/objects/balance_transaction.py
mollie/api/objects/base.py
mollie/api/objects/capture.py
mollie/api/objects/chargeback.py
mollie/api/objects/client.py
mollie/api/objects/client_link.py
mollie/api/objects/customer.py
mollie/api/objects/invoice.py
mollie/api/objects/issuer.py
mollie/api/objects/list.py
mollie/api/objects/mandate.py
mollie/api/objects/method.py
mollie/api/objects/onboarding.py
mollie/api/objects/order.py
mollie/api/objects/order_line.py
mollie/api/objects/organization.py
mollie/api/objects/payment.py
mollie/api/objects/payment_link.py
mollie/api/objects/permission.py
mollie/api/objects/profile.py
mollie/api/objects/refund.py
mollie/api/objects/settlement.py
mollie/api/objects/shipment.py
mollie/api/objects/subscription.py
mollie/api/objects/terminal.py
mollie/api/resources/__init__.py
mollie/api/resources/balances.py
mollie/api/resources/base.py
mollie/api/resources/captures.py
mollie/api/resources/chargebacks.py
mollie/api/resources/client_links.py
mollie/api/resources/clients.py
mollie/api/resources/customers.py
mollie/api/resources/invoices.py
mollie/api/resources/mandates.py
mollie/api/resources/methods.py
mollie/api/resources/onboarding.py
mollie/api/resources/order_lines.py
mollie/api/resources/orders.py
mollie/api/resources/organizations.py
mollie/api/resources/payment_links.py
mollie/api/resources/payments.py
mollie/api/resources/permissions.py
mollie/api/resources/profiles.py
mollie/api/resources/refunds.py
mollie/api/resources/settlements.py
mollie/api/resources/shipments.py
mollie/api/resources/subscriptions.py
mollie/api/resources/terminals.py
mollie_api_python-3.9.1.dist-info/licenses/LICENSE.txt
mollie_api_python-3.9.1.dist-info/METADATA
mollie_api_python-3.9.1.dist-info/WHEEL
mollie_api_python-3.9.1.dist-info/top_level.txt
mollie_api_python-3.9.1.dist-info/RECORD
