Metadata-Version: 2.4
Name: mollie-api-python
Version: 3.9.1
Summary: Mollie API client for Python
Home-page: https://github.com/mollie/mollie-api-python
Author: Mollie B.V.
Author-email: info@mollie.com
Maintainer: Four Digits B.V.
Maintainer-email: info@fourdigits.nl
License: BSD
Keywords: mollie,payment,service,ideal,creditcard,mistercash,bancontact,sofort,sofortbanking,sepa,paypal,paysafecard,podiumcadeaukaart,banktransfer,direct debit,belfius,belfius direct net,kbc,cbc,refunds,payments,gateway,gift cards,intersolve,fashioncheque,podium cadeaukaart,yourgift,vvv giftcard,webshop giftcard,nationale entertainment card,klarna pay later,klarna pay now,klarna slice it,przelewy24
Classifier: Programming Language :: Python
Classifier: Programming Language :: Python :: 3
Classifier: Development Status :: 5 - Production/Stable
Classifier: Intended Audience :: Developers
Classifier: License :: OSI Approved :: BSD License
Classifier: Topic :: Office/Business :: Financial
License-File: LICENSE.txt
Requires-Dist: requests
Requires-Dist: urllib3
Requires-Dist: requests_oauthlib
Dynamic: author
Dynamic: author-email
Dynamic: classifier
Dynamic: description
Dynamic: description-content-type
Dynamic: home-page
Dynamic: keywords
Dynamic: license
Dynamic: license-file
Dynamic: maintainer
Dynamic: maintainer-email
Dynamic: requires-dist
Dynamic: summary
